dctadam/Untitled-1.py
dctadam/__init__.py
dctadam/optimizer.py
dctadam/utils.py
dctadam-0.1.0.dist-info/METADATA
dctadam-0.1.0.dist-info/WHEEL
dctadam-0.1.0.dist-info/top_level.txt
dctadam-0.1.0.dist-info/RECORD
